huaweicloudsdksa/__init__.py
huaweicloudsdksa/v1/__init__.py
huaweicloudsdksa/v1/sa_async_client.py
huaweicloudsdksa/v1/sa_client.py
huaweicloudsdksa/v1/model/__init__.py
huaweicloudsdksa/v1/model/check_product_healthy_request.py
huaweicloudsdksa/v1/model/check_product_healthy_response.py
huaweicloudsdksa/v1/model/compliance.py
huaweicloudsdksa/v1/model/data_source.py
huaweicloudsdksa/v1/model/environment.py
huaweicloudsdksa/v1/model/event.py
huaweicloudsdksa/v1/model/events.py
huaweicloudsdksa/v1/model/geo.py
huaweicloudsdksa/v1/model/import_events_request.py
huaweicloudsdksa/v1/model/import_events_response.py
huaweicloudsdksa/v1/model/malware.py
huaweicloudsdksa/v1/model/malware_properties.py
huaweicloudsdksa/v1/model/network.py
huaweicloudsdksa/v1/model/product_info.py
huaweicloudsdksa/v1/model/remediation.py
huaweicloudsdksa/v1/model/resource.py
huaweicloudsdksa/v1/model/severity.py
huaweicloudsdksa/v1/model/threat_intel.py
huaweicloudsdksa/v1/model/threat_intel_properties.py
huaweicloudsdksa/v1/model/type.py
huaweicloudsdksa/v1/model/type_properties.py
huaweicloudsdksa/v1/model/vulnerability_patch.py
huaweicloudsdksa/v1/region/__init__.py
huaweicloudsdksa/v1/region/sa_region.py
huaweicloudsdksa/v2/__init__.py
huaweicloudsdksa/v2/sa_async_client.py
huaweicloudsdksa/v2/sa_client.py
huaweicloudsdksa/v2/model/__init__.py
huaweicloudsdksa/v2/model/action_info.py
huaweicloudsdksa/v2/model/action_instance_info.py
huaweicloudsdksa/v2/model/alert.py
huaweicloudsdksa/v2/model/alert_detail.py
huaweicloudsdksa/v2/model/alert_rule.py
huaweicloudsdksa/v2/model/alert_rule_metric.py
huaweicloudsdksa/v2/model/alert_rule_template.py
huaweicloudsdksa/v2/model/alert_rule_trigger.py
huaweicloudsdksa/v2/model/approve_opinion_detail.py
huaweicloudsdksa/v2/model/approve_playbook_info.py
huaweicloudsdksa/v2/model/audit_log_info.py
huaweicloudsdksa/v2/model/batch_order_alert_result.py
huaweicloudsdksa/v2/model/change_alert_request.py
huaweicloudsdksa-3.1.184.dist-info/METADATA
huaweicloudsdksa-3.1.184.dist-info/WHEEL
huaweicloudsdksa-3.1.184.dist-info/licenses/LICENSE
huaweicloudsdksa-3.1.184.dist-info/RECORD
